castle/__init__.py
castle/algorithms/__init__.py
castle/algorithms/anm/__init__.py
castle/algorithms/anm/_anm.py
castle/algorithms/ges/__init__.py
castle/algorithms/ges/ges.py
castle/algorithms/ges/functional/__init__.py
castle/algorithms/ges/functional/graph.py
castle/algorithms/ges/functional/utils.py
castle/algorithms/ges/operators/__init__.py
castle/algorithms/ges/operators/deleter.py
castle/algorithms/ges/operators/inserter.py
castle/algorithms/ges/operators/search.py
castle/algorithms/ges/score/__init__.py
castle/algorithms/ges/score/local_scores.py
castle/algorithms/gradient/__init__.py
castle/algorithms/gradient/corl/__init__.py
castle/algorithms/gradient/corl/torch/__init__.py
castle/algorithms/gradient/corl/torch/corl.py
castle/algorithms/gradient/corl/torch/frame/__init__.py
castle/algorithms/gradient/corl/torch/frame/_actor.py
castle/algorithms/gradient/corl/torch/frame/_critic.py
castle/algorithms/gradient/corl/torch/frame/_reward.py
castle/algorithms/gradient/corl/torch/frame/score_function.py
castle/algorithms/gradient/corl/torch/models/__init__.py
castle/algorithms/gradient/corl/torch/models/_base_network.py
castle/algorithms/gradient/corl/torch/models/decoders.py
castle/algorithms/gradient/corl/torch/models/encoders.py
castle/algorithms/gradient/corl/torch/utils/__init__.py
castle/algorithms/gradient/corl/torch/utils/data_loader.py
castle/algorithms/gradient/corl/torch/utils/graph_analysis.py
castle/algorithms/gradient/corl/torch/utils/validation.py
castle/algorithms/gradient/dag_gnn/__init__.py
castle/algorithms/gradient/dag_gnn/torch/__init__.py
castle/algorithms/gradient/dag_gnn/torch/dag_gnn.py
castle/algorithms/gradient/dag_gnn/torch/models/__init__.py
castle/algorithms/gradient/dag_gnn/torch/models/modules.py
castle/algorithms/gradient/dag_gnn/torch/utils/__init__.py
castle/algorithms/gradient/dag_gnn/torch/utils/functions.py
castle/algorithms/gradient/gae/__init__.py
castle/algorithms/gradient/gae/torch/__init__.py
gcastle-1.0.4.dist-info/METADATA
gcastle-1.0.4.dist-info/WHEEL
gcastle-1.0.4.dist-info/top_level.txt
gcastle-1.0.4.dist-info/RECORD
