Metadata-Version: 2.1
Name: gcastle
Version: 1.0.4
Summary: gCastle is the fundamental package for causal structure learning with Python.
Home-page: https://github.com/huawei-noah/trustworthyAI/tree/master/gcastle
Author: Huawei Noah's Ark Lab
Author-email: zhangkeli1@huawei.com
License: Apache License 2.0
Classifier: Programming Language :: Python :: 3
Classifier: License :: OSI Approved :: Apache Software License
Classifier: Operating System :: OS Independent
Requires-Python: >=3.6
Requires-Dist: matplotlib >=2.1.2
Requires-Dist: networkx >=2.5
Requires-Dist: numpy >=1.19.1
Requires-Dist: pandas >=0.22.0
Requires-Dist: scikit-learn >=0.21.1
Requires-Dist: scipy >=1.7.3
Requires-Dist: tqdm >=4.48.2
